pyraliddemo/__init__.py
pyraliddemo/example/__init__.py
pyraliddemo/example/classes.py
pyraliddemo/example/hello.py
pyraliddemo/example/math.py
pyraliddemo/tests/__init__.py
pyraliddemo/tests/test_example.py
pyraliddemo-0.0.2.data/scripts/example_script.py
scripts/__init__.py
scripts/example_script.py
pyraliddemo-0.0.2.dist-info/LICENCE.txt
pyraliddemo-0.0.2.dist-info/METADATA
pyraliddemo-0.0.2.dist-info/WHEEL
pyraliddemo-0.0.2.dist-info/top_level.txt
pyraliddemo-0.0.2.dist-info/RECORD
