Metadata-Version: 2.1
Name: pyraliddemo
Version: 0.0.2
Summary: Demo package made using the Pyralid Template
Home-page: https://github.com/sfarrens/pyraliddemo
Author: Samuel Farrens
Author-email: samuel.farrens@cea.fr
License: MIT
Platform: UNKNOWN
Classifier: License :: OSI Approved :: MIT License
Classifier: Programming Language :: Python
Classifier: Programming Language :: Python :: 3.6
Classifier: Programming Language :: Python :: 3.7
Classifier: Programming Language :: Python :: 3.8
Classifier: Programming Language :: Python :: 3.9
Classifier: Operating System :: Unix
Classifier: Operating System :: MacOS
Requires-Python: >=3.6
Requires-Dist: importlib-metadata (==3.1.1)
Requires-Dist: matplotlib (==3.3.3)
Requires-Dist: numpy (==1.19.4)
Provides-Extra: develop
Requires-Dist: coverage (==5.3) ; extra == 'develop'
Requires-Dist: nose (==1.3.7) ; extra == 'develop'
Requires-Dist: pytest (==6.1.2) ; extra == 'develop'
Requires-Dist: pytest-cov (==2.10.1) ; extra == 'develop'
Requires-Dist: pytest-pep8 (==1.0.6) ; extra == 'develop'
Requires-Dist: pytest-emoji (==0.2.0) ; extra == 'develop'
Requires-Dist: pytest-flake8 (==1.0.6) ; extra == 'develop'
Requires-Dist: wemake-python-styleguide (==0.14.1) ; extra == 'develop'
Requires-Dist: jupyter (==1.0.0) ; extra == 'develop'
Requires-Dist: nbsphinx (==0.8.0) ; extra == 'develop'
Requires-Dist: nbsphinx-link (==1.3.0) ; extra == 'develop'
Requires-Dist: numpydoc (==1.1.0) ; extra == 'develop'
Requires-Dist: sphinx (==3.3.1) ; extra == 'develop'
Requires-Dist: sphinxcontrib-bibtex (==1.0.0) ; extra == 'develop'
Requires-Dist: sphinxawesome-theme (==1.18.0) ; extra == 'develop'
